MANIFEST.in
distribute_setup.py
setup.py
docs/Makefile
guachi/__init__.py
guachi/config.py
guachi/database.py
guachi.egg-info/PKG-INFO
guachi.egg-info/SOURCES.txt
guachi.egg-info/dependency_links.txt
guachi.egg-info/top_level.txt
guachi/tests/test_configmapper.py
guachi/tests/test_configurations.py
guachi/tests/test_database.py
guachi/tests/test_integration.py