Metadata-Version: 1.0
Name: guachi
Version: 0.0.3
Summary: Global, persistent configurations as dictionaries
Home-page: http://code.google.com/p/guachi
Author: Alfredo Deza
Author-email: alfredodeza [at] gmail [dot] com
License: MIT
Keywords: configuration management persistent dictionaries dictionary parse map mapping
Platform: UNKNOWN
Classifier: Development Status :: 4 - Beta
Classifier: Intended Audience :: Developers
Classifier: License :: OSI Approved :: MIT License
Classifier: Topic :: Software Development :: Build Tools
Classifier: Programming Language :: Python :: 2.5
Classifier: Programming Language :: Python :: 2.6
Classifier: Programming Language :: Python :: 2.7
